ai_energy_benchmarks/__init__.py
ai_energy_benchmarks/py.typed
ai_energy_benchmarks/runner.py
ai_energy_benchmarks/backends/__init__.py
ai_energy_benchmarks/backends/base.py
ai_energy_benchmarks/backends/pytorch.py
ai_energy_benchmarks/backends/vllm.py
ai_energy_benchmarks/cli/__init__.py
ai_energy_benchmarks/cli/profile.py
ai_energy_benchmarks/config/__init__.py
ai_energy_benchmarks/config/parser.py
ai_energy_benchmarks/config/reasoning_formats.yaml
ai_energy_benchmarks/datasets/__init__.py
ai_energy_benchmarks/datasets/base.py
ai_energy_benchmarks/datasets/huggingface.py
ai_energy_benchmarks/executors/__init__.py
ai_energy_benchmarks/executors/energy_aware.py
ai_energy_benchmarks/executors/genai_perf.py
ai_energy_benchmarks/formatters/__init__.py
ai_energy_benchmarks/formatters/base.py
ai_energy_benchmarks/formatters/episode.py
ai_energy_benchmarks/formatters/harmony.py
ai_energy_benchmarks/formatters/parameter.py
ai_energy_benchmarks/formatters/prefix.py
ai_energy_benchmarks/formatters/registry.py
ai_energy_benchmarks/formatters/system_prompt.py
ai_energy_benchmarks/metrics/__init__.py
ai_energy_benchmarks/metrics/base.py
ai_energy_benchmarks/metrics/codecarbon.py
ai_energy_benchmarks/profiles/__init__.py
ai_energy_benchmarks/profiles/definitions.py
ai_energy_benchmarks/reporters/__init__.py
ai_energy_benchmarks/reporters/base.py
ai_energy_benchmarks/reporters/csv_reporter.py
ai_energy_benchmarks/utils/__init__.py
ai_energy_benchmarks/utils/gpu.py
ai_energy_benchmarks-0.0.7.dist-info/licenses/LICENSE
ai_energy_benchmarks-0.0.7.dist-info/METADATA
ai_energy_benchmarks-0.0.7.dist-info/WHEEL
ai_energy_benchmarks-0.0.7.dist-info/entry_points.txt
ai_energy_benchmarks-0.0.7.dist-info/top_level.txt
ai_energy_benchmarks-0.0.7.dist-info/RECORD
