Metadata-Version: 2.4
Name: ai_energy_benchmarks
Version: 0.0.7
Summary: Modular benchmarking framework for AI energy measurements - POC Phase
Author-email: NeuralWatt <info@neuralwatt.com>
License: MIT
Project-URL: Homepage, https://github.com/neuralwatt/ai_energy_benchmarks
Project-URL: Documentation, https://github.com/neuralwatt/ai_energy_benchmarks/tree/main/docs
Project-URL: Repository, https://github.com/neuralwatt/ai_energy_benchmarks
Project-URL: Issues, https://github.com/neuralwatt/ai_energy_benchmarks/issues
Keywords: ai,energy,benchmarks,carbon,emissions,gpu
Classifier: Development Status :: 2 - Pre-Alpha
Classifier: Intended Audience :: Developers
Classifier: Intended Audience :: Science/Research
Classifier: License :: OSI Approved :: MIT License
Classifier: Programming Language :: Python :: 3
Classifier: Programming Language :: Python :: 3.10
Classifier: Programming Language :: Python :: 3.11
Classifier: Programming Language :: Python :: 3.12
Classifier: Topic :: Scientific/Engineering :: Artificial Intelligence
Requires-Python: >=3.10
License-File: LICENSE
Requires-Dist: requests>=2.31.0
Requires-Dist: datasets>=2.14.0
Requires-Dist: codecarbon>=2.3.0
Requires-Dist: omegaconf>=2.3.0
Requires-Dist: pyyaml>=6.0
Provides-Extra: dev
Requires-Dist: pytest>=7.4.0; extra == "dev"
Requires-Dist: pytest-asyncio>=0.21.0; extra == "dev"
Requires-Dist: pytest-cov>=4.1.0; extra == "dev"
Requires-Dist: pytest-mock>=3.11.0; extra == "dev"
Requires-Dist: ruff>=0.1.0; extra == "dev"
Requires-Dist: mypy>=1.5.0; extra == "dev"
Requires-Dist: black>=23.7.0; extra == "dev"
Requires-Dist: pre-commit>=3.3.0; extra == "dev"
Provides-Extra: pytorch
Requires-Dist: torch>=2.0.0; extra == "pytorch"
Requires-Dist: transformers>=4.30.0; extra == "pytorch"
Requires-Dist: accelerate; extra == "pytorch"
Provides-Extra: profiling
Requires-Dist: pandas>=2.0.0; extra == "profiling"
Provides-Extra: all
Requires-Dist: torch>=2.0.0; extra == "all"
Requires-Dist: transformers>=4.30.0; extra == "all"
Requires-Dist: accelerate; extra == "all"
Requires-Dist: pandas>=2.0.0; extra == "all"
Requires-Dist: pytest>=7.4.0; extra == "all"
Requires-Dist: pytest-asyncio>=0.21.0; extra == "all"
Requires-Dist: pytest-cov>=4.1.0; extra == "all"
Requires-Dist: pytest-mock>=3.11.0; extra == "all"
Requires-Dist: ruff>=0.1.0; extra == "all"
Requires-Dist: mypy>=1.5.0; extra == "all"
Requires-Dist: black>=23.7.0; extra == "all"
Requires-Dist: pre-commit>=3.3.0; extra == "all"
Dynamic: license-file
